<?xml version="1.0" encoding="UTF-8"?>

<channer>
  <link>https://naver.com</link>
  <title>news</title>
  <data>2022.05.12</data>
  <writer>신동원 기자</writer>
  <item>
    <link>https://n.news.naver.com/article/661/0000006758?cds=news_media_pctype=editn</link>
    <title>기르던 푸들 생매장 견주 등 2명 검찰 송치</title>
    <data>2022.05.12</data>
    <writer>신동원 기자</writer>
    <description>
  제주에서 발생한 생매장 푸들 학대사건의 피의자 2명이 검찰 수사를 받게 됐습니다.

  12일 제주서부경찰서에 따르면 기르던 강아지를 산 채로 땅에 묻은 보호자(견주) A씨 등 2명을 최근 동물보호법 위반 혐의로 검찰에 송치했습니다.

  경찰 조사 결과, 이들은 지난달 19일 오전 3시쯤 제주시 내도동에 있는 도근천 인근에 살아있는 푸들 강아지를 코와 입만 내놓은 채 묻은 혐의를 받습니다.

  이 강아지는 같은 날 오전 8시 50분께 주변을 지나던 시민에 의해 발견됐습니다.

  이들은 참고인 신분으로 경찰 조사를 받았던 지난달 20일에는 강아지를 잃어버렸다는 취지로 진술을 한 것으로 전해졌습니다.

  이튿날인 4월 21일 언론을 통해 이 사건이 일파만파 확산되자 경찰에 자진 출석해 자수했습니다.

  자진 출두 당시에도 이들은 처음에 죽은 상태의 강아지를 묻었다고 진술했으나, 경찰 수사 결과 사실이 아님이 밝혀졌습니다.

  경찰 관계자는 "처음 조사 당시에는 강아지가 죽은 상태였다고 진술했으나 폐쇄회로(CC)TV 영상 등 확보한 증거자료를 분석한 결과 피해 강아지가 죽은 상태가 아니라는 것을 확인했다"라며, "이를 토대로 보강 수사를 벌여 A씨 등으로부터 살아있는 상태에서 강아지를 묻었다고 시인받았다"라고 밝혔습니다.

  한편, 강아지를 처음 발견해 구조한 허재문씨(62)에 따르면 어디선가 '우, 우, 우' 소리가 나서 인근을 둘러보던 중 땅속에서 코만 나와 있는 강아지를 발견했습니다.

  강아지는 발견 당시 코와 주둥이 등 숨구멍을 제외한 몸체가 땅 속에 파묻혀 있었습니다.

  파묻힌 강아지 입에는 하얗게 거품 물려 있었습니다.

  허씨는 곧바로 주위의 돌들을 걷어내고 맨손으로 땅을 파 강아지를 땅 위로 구출했습니다.

  구조 직후 강아지는 등뼈와 갈비뼈가 고스란히 노출될 정도로 매우 야윈 상태였습니다.

  불안감 때문인지 몸을 벌벌 떨었고 눈물을 흘려 얼굴이 새카맣게 되었습니다.

  너무 지쳐 있어 제대로 짖지도 못했습니다. 제대로 기는 것조차 힘겨워 보였습니다.

  강아지는 현장에 출동한 경찰에 인계되었다가 다시 제주동물호보센터로 옮겨져 치료를 받았습니다.

  이후 새 임시보호자를 만나 '다미'라는 새 이름을 얻고 안정를 찾아가고 있는 것으로 전해졌습니다.

  앞서 지난달 13일에는 주둥이와 발이 묶인 강아지가 제주에서 발견돼 전국적인 공분을 산 바 있습니다.

  현재 경찰이 수사를 벌이고 있으나 현장 인근 CCTV 등 증거가 부족해 수사에 난항을 겪고 있습니다.

  한편, 지난해 제주에서 수사가 진행된 동물학대 사건은 모두 27건이었습니다. 이 가운데 정식으로 입건된 피의자는 14건에 불과했습니다.

  현행 동물보호법에 따르면 동물을 학대해 죽음에 이르게 할 경우 3년 이하 징역 또는 3천만 원 이하의 벌금형에 처해집니다. 또 이번 학대 사건처럼 죽음에 이르진 않았지만 동물을 학대한 경우에는 2년 이하의 징역 또는 2천만 원 이하의 벌금형을 받을 수 있습니다.
    </description>
  </item>
</channer>
